getgdelt/__init__.py
getgdelt-1.0.0.dist-info/LICENSE.rtf
getgdelt-1.0.0.dist-info/METADATA
getgdelt-1.0.0.dist-info/WHEEL
getgdelt-1.0.0.dist-info/top_level.txt
getgdelt-1.0.0.dist-info/RECORD
