Metadata-Version: 2.1
Name: getgdelt
Version: 1.0.0
Summary: Get and use gdelt data more reliably without hardware limitation.
Home-page: https://github.com/syfyufei/getgdelt
Author: Sun Yufei
Author-email: syfyufei@gmail.com
License: UNKNOWN
Platform: UNKNOWN
Classifier: Programming Language :: Python :: 3
Classifier: License :: OSI Approved :: MIT License
Classifier: Operating System :: OS Independent
Requires-Python: >=3.6
